vidkit/__init__.py
vidkit/core.py
vidkit-0.1.3.2.dist-info/LICENSE
vidkit-0.1.3.2.dist-info/METADATA
vidkit-0.1.3.2.dist-info/WHEEL
vidkit-0.1.3.2.dist-info/top_level.txt
vidkit-0.1.3.2.dist-info/RECORD
