Metadata-Version: 2.1
Name: vidkit
Version: 0.1.3.2
Summary: A Python package for generating videos from JSON specifications
Home-page: https://github.com/SpyC0der77/vidkit
Author: Carter Stach
Author-email: carter.stach@gmail.com
Keywords: video generation,json,moviepy,video editing
Classifier: Development Status :: 3 - Alpha
Classifier: Intended Audience :: Developers
Classifier: License :: OSI Approved :: MIT License
Classifier: Operating System :: OS Independent
Classifier: Programming Language :: Python :: 3
Classifier: Programming Language :: Python :: 3.6
Classifier: Programming Language :: Python :: 3.7
Classifier: Programming Language :: Python :: 3.8
Classifier: Programming Language :: Python :: 3.9
Classifier: Programming Language :: Python :: 3.10
Classifier: Programming Language :: Python :: 3.11
Classifier: Programming Language :: Python :: 3.12
Requires-Python: >=3.6
License-File: LICENSE
Requires-Dist: moviepy>=2.0.0
Requires-Dist: Pillow>=10.2.0
Requires-Dist: numpy>=1.25.0
Requires-Dist: mutagen>=1.45.0
